{
  "id": "007",
  "title": "Puzzle 007",
  "size": {
    "rows": 5,
    "cols": 5
  },
  "grid": [
    [
      "",
      "",
      "",
      "",
      ""
    ],
    [
      "",
      "#",
      "",
      "",
      ""
    ],
    [
      "",
      "",
      "",
      "",
      ""
    ],
    [
      "",
      "",
      "",
      "#",
      ""
    ],
    [
      "",
      "",
      "",
      "",
      ""
    ]
  ],
  "solution": [
    [
      "B",
      "R",
      "A",
      "M",
      "E"
    ],
    [
      "E",
      "#",
      "O",
      "F",
      "F"
    ],
    [
      "T",
      "A",
      "R",
      "D",
      "E"
    ],
    [
      "T",
      "A",
      "T",
      "#",
      "B"
    ],
    [
      "E",
      "R",
      "A",
      "T",
      "O"
    ]
  ],
  "clues": {
    "across": [
      {
        "number": 1,
        "clue": "Voglie smodate",
        "row": 0,
        "col": 0,
        "length": 5,
        "direction": "across"
      },
      {
        "number": 7,
        "clue": "Spento sui pulsanti",
        "row": 1,
        "col": 2,
        "length": 3,
        "direction": "across"
      },
      {
        "number": 8,
        "clue": "Lente, pigre",
        "row": 2,
        "col": 0,
        "length": 5,
        "direction": "across"
      },
      {
        "number": 10,
        "clue": "Tribunale Amministrativo Regionale",
        "row": 3,
        "col": 0,
        "length": 3,
        "direction": "across"
      },
      {
        "number": 12,
        "clue": "Una Musa",
        "row": 4,
        "col": 0,
        "length": 5,
        "direction": "across"
      }
    ],
    "down": [
      {
        "number": 1,
        "clue": "Il nome della Midler",
        "row": 0,
        "col": 0,
        "length": 5,
        "direction": "down"
      },
      {
        "number": 3,
        "clue": "La più grossa arteria",
        "row": 0,
        "col": 2,
        "length": 5,
        "direction": "down"
      },
      {
        "number": 4,
        "clue": "Movimento Federativo Democratico",
        "row": 0,
        "col": 3,
        "length": 3,
        "direction": "down"
      },
      {
        "number": 5,
        "clue": "Giovinetto di delicata bellezza",
        "row": 0,
        "col": 4,
        "length": 5,
        "direction": "down"
      },
      {
        "number": 9,
        "clue": "Passa per Soletta",
        "row": 2,
        "col": 1,
        "length": 3,
        "direction": "down"
      }
    ]
  }
}