{
  "id": "093",
  "title": "Puzzle 093",
  "size": {
    "rows": 5,
    "cols": 5
  },
  "grid": [
    [
      "",
      "",
      "",
      "",
      ""
    ],
    [
      "",
      "",
      "",
      "",
      ""
    ],
    [
      "",
      "",
      "#",
      "",
      ""
    ],
    [
      "",
      "",
      "",
      "",
      ""
    ],
    [
      "",
      "",
      "",
      "",
      ""
    ]
  ],
  "solution": [
    [
      "O",
      "C",
      "O",
      "N",
      "E"
    ],
    [
      "R",
      "E",
      "C",
      "I",
      "T"
    ],
    [
      "I",
      "S",
      "#",
      "T",
      "N"
    ],
    [
      "O",
      "T",
      "I",
      "T",
      "E"
    ],
    [
      "N",
      "A",
      "D",
      "I",
      "A"
    ]
  ],
  "clues": {
    "across": [
      {
        "number": 1,
        "clue": "Lucia comica",
        "row": 0,
        "col": 0,
        "length": 5,
        "direction": "across"
      },
      {
        "number": 6,
        "clue": "Racconto...alla francese",
        "row": 1,
        "col": 0,
        "length": 5,
        "direction": "across"
      },
      {
        "number": 7,
        "clue": "In mezzo al prisma",
        "row": 2,
        "col": 0,
        "length": 2,
        "direction": "across"
      },
      {
        "number": 8,
        "clue": "Nei timoni e nelle catene",
        "row": 2,
        "col": 3,
        "length": 2,
        "direction": "across"
      },
      {
        "number": 9,
        "clue": "Affezione dell'orecchio",
        "row": 3,
        "col": 0,
        "length": 5,
        "direction": "across"
      },
      {
        "number": 11,
        "clue": "Nome di donna",
        "row": 4,
        "col": 0,
        "length": 5,
        "direction": "across"
      }
    ],
    "down": [
      {
        "number": 1,
        "clue": "Un modello della Ford",
        "row": 0,
        "col": 0,
        "length": 5,
        "direction": "down"
      },
      {
        "number": 2,
        "clue": "Un recipiente intrecciato",
        "row": 0,
        "col": 1,
        "length": 5,
        "direction": "down"
      },
      {
        "number": 3,
        "clue": "Poco in centro",
        "row": 0,
        "col": 2,
        "length": 2,
        "direction": "down"
      },
      {
        "number": 4,
        "clue": "Il Francesco Saverio storico statista",
        "row": 0,
        "col": 3,
        "length": 5,
        "direction": "down"
      },
      {
        "number": 5,
        "clue": "Della regione del Mongibello",
        "row": 0,
        "col": 4,
        "length": 5,
        "direction": "down"
      },
      {
        "number": 10,
        "clue": "Come sopra, in breve",
        "row": 3,
        "col": 2,
        "length": 2,
        "direction": "down"
      }
    ]
  }
}