{
  "id": "387",
  "title": "Puzzle 387",
  "size": {
    "rows": 7,
    "cols": 7
  },
  "grid": [
    [
      "",
      "",
      "",
      "",
      "#",
      "",
      ""
    ],
    [
      "",
      "",
      "",
      "#",
      "",
      "",
      ""
    ],
    [
      "",
      "",
      "",
      "",
      "",
      "",
      ""
    ],
    [
      "",
      "",
      "#",
      "",
      "#",
      "",
      ""
    ],
    [
      "",
      "",
      "",
      "",
      "",
      "",
      ""
    ],
    [
      "",
      "",
      "",
      "#",
      "",
      "",
      ""
    ],
    [
      "",
      "",
      "#",
      "",
      "",
      "",
      ""
    ]
  ],
  "solution": [
    [
      "I",
      "A",
      "T",
      "O",
      "#",
      "V",
      "H"
    ],
    [
      "N",
      "B",
      "A",
      "#",
      "L",
      "E",
      "U"
    ],
    [
      "T",
      "O",
      "P",
      "L",
      "E",
      "S",
      "S"
    ],
    [
      "O",
      "M",
      "#",
      "A",
      "#",
      "S",
      "S"
    ],
    [
      "P",
      "A",
      "S",
      "I",
      "F",
      "A",
      "E"
    ],
    [
      "P",
      "S",
      "C",
      "#",
      "O",
      "T",
      "I"
    ],
    [
      "I",
      "O",
      "#",
      "A",
      "N",
      "O",
      "N"
    ]
  ],
  "clues": {
    "across": [
      {
        "number": 1,
        "clue": "Un'interruzione in una sequenza continua",
        "row": 0,
        "col": 0,
        "length": 4,
        "direction": "across"
      },
      {
        "number": 5,
        "clue": "Scrisse I miserabili (iniz.)",
        "row": 0,
        "col": 5,
        "length": 2,
        "direction": "across"
      },
      {
        "number": 7,
        "clue": "Una lega per il basket (sigla)",
        "row": 1,
        "col": 0,
        "length": 3,
        "direction": "across"
      },
      {
        "number": 8,
        "clue": "Una sigla per Grasso",
        "row": 1,
        "col": 4,
        "length": 3,
        "direction": "across"
      },
      {
        "number": 9,
        "clue": "Audace costume da spiaggia",
        "row": 2,
        "col": 0,
        "length": 7,
        "direction": "across"
      },
      {
        "number": 11,
        "clue": "Vecchia marca di camion",
        "row": 3,
        "col": 0,
        "length": 2,
        "direction": "across"
      },
      {
        "number": 13,
        "clue": "Crossare al centro",
        "row": 3,
        "col": 5,
        "length": 2,
        "direction": "across"
      },
      {
        "number": 14,
        "clue": "La madre del Minotauro",
        "row": 4,
        "col": 0,
        "length": 7,
        "direction": "across"
      },
      {
        "number": 17,
        "clue": "Patto di Stabilità e Crescita (sigla)",
        "row": 5,
        "col": 0,
        "length": 3,
        "direction": "across"
      },
      {
        "number": 18,
        "clue": "Organizzazione Turistica Italiana",
        "row": 5,
        "col": 4,
        "length": 3,
        "direction": "across"
      },
      {
        "number": 19,
        "clue": "É assoluto per Hegel",
        "row": 6,
        "col": 0,
        "length": 2,
        "direction": "across"
      },
      {
        "number": 20,
        "clue": "Anonimo in breve",
        "row": 6,
        "col": 3,
        "length": 4,
        "direction": "across"
      }
    ],
    "down": [
      {
        "number": 1,
        "clue": "Incagli, impedimenti",
        "row": 0,
        "col": 0,
        "length": 7,
        "direction": "down"
      },
      {
        "number": 2,
        "clue": "Uno stomaco dei ruminanti",
        "row": 0,
        "col": 1,
        "length": 7,
        "direction": "down"
      },
      {
        "number": 3,
        "clue": "Segue tip",
        "row": 0,
        "col": 2,
        "length": 3,
        "direction": "down"
      },
      {
        "number": 5,
        "clue": "Sottoposto a maltrattamenti",
        "row": 0,
        "col": 5,
        "length": 7,
        "direction": "down"
      },
      {
        "number": 6,
        "clue": "Fra Barack e Obama",
        "row": 0,
        "col": 6,
        "length": 7,
        "direction": "down"
      },
      {
        "number": 8,
        "clue": "Le hanno i leoni e le gazzelle",
        "row": 1,
        "col": 4,
        "length": 2,
        "direction": "down"
      },
      {
        "number": 10,
        "clue": "Voci lamentevoli",
        "row": 2,
        "col": 3,
        "length": 3,
        "direction": "down"
      },
      {
        "number": 15,
        "clue": "Due di scena",
        "row": 4,
        "col": 2,
        "length": 2,
        "direction": "down"
      },
      {
        "number": 16,
        "clue": "Si accende per asciugare i capelli",
        "row": 4,
        "col": 4,
        "length": 3,
        "direction": "down"
      }
    ]
  }
}